rl_helper/__init__.py
rl_helper/envhelper.py
rl_helper/exps.py
rl_helper/fps.py
rl_helper/keyboard.py
rl_helper-0.4.dist-info/METADATA
rl_helper-0.4.dist-info/WHEEL
rl_helper-0.4.dist-info/top_level.txt
rl_helper-0.4.dist-info/RECORD
